pycirclemedianfilter.cpython-310-x86_64-linux-gnu.so
pycirclemedianfilter-0.1.6.dist-info/METADATA
pycirclemedianfilter-0.1.6.dist-info/WHEEL
pycirclemedianfilter-0.1.6.dist-info/top_level.txt
pycirclemedianfilter-0.1.6.dist-info/RECORD
pycirclemedianfilter-0.1.6.dist-info/licenses/LICENSE
