Metadata-Version: 2.4
Name: pycirclemedianfilter
Version: 0.1.6
Summary: A Circle Median Filter package for Python
Home-page: https://github.com/mstorath/CircleMedianFilter
Author: Martin Storath
Author-email: martin.storath@thws.de
Classifier: Programming Language :: Python :: 3
Classifier: Operating System :: OS Independent
Requires-Python: >=3.9
License-File: LICENSE
Requires-Dist: numpy
Requires-Dist: pybind11
Dynamic: author
Dynamic: author-email
Dynamic: classifier
Dynamic: description
Dynamic: description-content-type
Dynamic: home-page
Dynamic: license-file
Dynamic: requires-dist
Dynamic: requires-python
Dynamic: summary
